AUTHORS
HACKING
LICENSE
MANIFEST.in
README.rst
setup.cfg
setup.py
examples/avahi.py
examples/dispatch_gevent.py
examples/listnames.py
examples/methodcall.py
examples/signal.py
lib/python_tdbus.egg-info/PKG-INFO
lib/python_tdbus.egg-info/SOURCES.txt
lib/python_tdbus.egg-info/dependency_links.txt
lib/python_tdbus.egg-info/top_level.txt
lib/tdbus/__init__.py
lib/tdbus/_tdbus.c
lib/tdbus/connection.py
lib/tdbus/gevent.py
lib/tdbus/handler.py
lib/tdbus/loop.py
lib/tdbus/select.py
test/test_connection.py
test/test_message.py