Metadata-Version: 1.1
Name: python-tdbus
Version: 0.10
Summary: A Python interface to D-BUS
Home-page: https://github.com/hmvp/python-tdbus
Author: Hmvp, Geert Jansen
Author-email: github@hmvp.nl
License: MIT
Platform: UNKNOWN
Classifier: Development Status :: 4 - Beta
Classifier: License :: OSI Approved :: MIT License
Classifier: Operating System :: POSIX
Classifier: Programming Language :: Python :: 2.6
Classifier: Programming Language :: Python :: 2.7
Classifier: Programming Language :: Python :: 3.3
Classifier: Programming Language :: Python :: 3.4
Classifier: Programming Language :: Python :: 3.5
